moonpie/__init__.py
moonpie/__main__.py
moonpie/ast_nodes.py
moonpie/evaluator.py
moonpie/lexer.py
moonpie/lua_builtins.py
moonpie/lua_interpreter.py
moonpie/lua_object.py
moonpie/lua_token.py
moonpie/parser.py
moonpie-0.1.0.dist-info/licenses/LICENSE
moonpie-0.1.0.dist-info/METADATA
moonpie-0.1.0.dist-info/WHEEL
moonpie-0.1.0.dist-info/entry_points.txt
moonpie-0.1.0.dist-info/top_level.txt
moonpie-0.1.0.dist-info/RECORD
