Metadata-Version: 2.4
Name: moonpie
Version: 0.1.0
Summary: A Lua interpreter written in Python
Author-email: MoonPie <java4life@gmail.com>
License: MIT
Project-URL: Homepage, https://github.com/rhulha/MoonPie
Project-URL: Documentation, https://github.com/rhulha/MoonPie#readme
Project-URL: Repository, https://github.com/rhulha/MoonPie
Project-URL: Bug Reports, https://github.com/rhulha/MoonPie/issues
Keywords: lua,interpreter,scripting,language
Classifier: Development Status :: 4 - Beta
Classifier: Intended Audience :: Developers
Classifier: License :: OSI Approved :: MIT License
Classifier: Operating System :: OS Independent
Classifier: Programming Language :: Python :: 3
Classifier: Programming Language :: Python :: 3.7
Classifier: Programming Language :: Python :: 3.8
Classifier: Programming Language :: Python :: 3.9
Classifier: Programming Language :: Python :: 3.10
Classifier: Programming Language :: Python :: 3.11
Classifier: Programming Language :: Python :: 3.12
Classifier: Topic :: Software Development :: Interpreters
Classifier: Topic :: Software Development :: Libraries :: Python Modules
Requires-Python: >=3.7
License-File: LICENSE
Provides-Extra: dev
Requires-Dist: pytest>=6.0; extra == "dev"
Requires-Dist: black; extra == "dev"
Requires-Dist: flake8; extra == "dev"
Dynamic: license-file
